lab1/half_adder.v
module half_adder(input a, b, output s,c);
 xor(s,a,b);
 and(c,a,b);
endmodule

lab1/full_adder.v
module full_adder(input a, b, cin, output s, cout);
 wire stemp, ctemp1, ctemp2;

 half_adder ha1(.a(a), .b(b), .s(stemp), .c(ctemp1));
 half_adder ha2(.a(stemp), .b(cin), .s(s), .c(ctemp2));
 or(cout, ctemp1, ctemp2);

endmodule

lab1/adder_4bit.v
module adder_4bit(input [3:0] a, b, input cin, output [3:0] s, output cout);
 wire c1, c2, c3;

 full_adder fa0(.a(a[0]), .b(b[0]), .cin(cin), .s(s[0]), .cout(c1));
 full_adder fa1(.a(a[1]), .b(b[1]), .cin(c1), .s(s[1]), .cout(c2));
 full_adder fa2(.a(a[2]), .b(b[2]), .cin(c2), .s(s[2]), .cout(c3));
 full_adder fa3(.a(a[3]), .b(b[3]), .cin(c3), .s(s[3]), .cout(cout));

endmodule;

lab1/adder_4bit_tb.v
`timescale 1ns/1ps

module adder_4bit_tb();
 reg [3:0]a, b;
 reg cin;
 wire cout;
 wire [3:0] s;

 adder_4bit a4b(.a(a), .b(b), .cin(cin), .s(s), .cout(cout));

 integer i, j, k;

 initial begin
  $dumpfile("adder_4bit.vcd");
  $dumpvars(0,a4b);

	for (k = 0; k < 2; k = k + 1) begin          // cin
	 	for (i = 0; i < 16; i = i + 1) begin        // a
	  	for (j = 0; j < 16; j = j + 1) begin      // b
	   		a = i; b = j; cin = k;
	   		#100;
	 		end 
	 	end 
	end
  $finish;
 end 
endmodule

lab1/adder_4bit.vcd
$date
	Thu Jun 18 23:21:31 2026
$end
$version
	Icarus Verilog
$end
$timescale
	1ps
$end
$scope module adder_4bit_tb $end
$scope module a4b $end
$var wire 4 ! a [3:0] $end
$var wire 4 " b [3:0] $end
$var wire 1 # cin $end
$var wire 4 $ s [3:0] $end
$var wire 1 % cout $end
$var wire 1 & c3 $end
$var wire 1 ' c2 $end
$var wire 1 ( c1 $end
$scope module fa0 $end
$var wire 1 ) a $end
$var wire 1 * b $end
$var wire 1 # cin $end
$var wire 1 ( cout $end
$var wire 1 + stemp $end
$var wire 1 , s $end
$var wire 1 - ctemp2 $end
$var wire 1 . ctemp1 $end
$scope module ha1 $end
$var wire 1 ) a $end
$var wire 1 * b $end
$var wire 1 . c $end
$var wire 1 + s $end
$upscope $end
$scope module ha2 $end
$var wire 1 + a $end
$var wire 1 # b $end
$var wire 1 - c $end
$var wire 1 , s $end
$upscope $end
$upscope $end
$scope module fa1 $end
$var wire 1 / a $end
$var wire 1 0 b $end
$var wire 1 ( cin $end
$var wire 1 ' cout $end
$var wire 1 1 stemp $end
$var wire 1 2 s $end
$var wire 1 3 ctemp2 $end
$var wire 1 4 ctemp1 $end
$scope module ha1 $end
$var wire 1 / a $end
$var wire 1 0 b $end
$var wire 1 4 c $end
$var wire 1 1 s $end
$upscope $end
$scope module ha2 $end
$var wire 1 1 a $end
$var wire 1 ( b $end
$var wire 1 3 c $end
$var wire 1 2 s $end
$upscope $end
$upscope $end
$scope module fa2 $end
$var wire 1 5 a $end
$var wire 1 6 b $end
$var wire 1 ' cin $end
$var wire 1 & cout $end
$var wire 1 7 stemp $end
$var wire 1 8 s $end
$var wire 1 9 ctemp2 $end
$var wire 1 : ctemp1 $end
$scope module ha1 $end
$var wire 1 5 a $end
$var wire 1 6 b $end
$var wire 1 : c $end
$var wire 1 7 s $end
$upscope $end
$scope module ha2 $end
$var wire 1 7 a $end
$var wire 1 ' b $end
$var wire 1 9 c $end
$var wire 1 8 s $end
$upscope $end
$upscope $end
$scope module fa3 $end
$var wire 1 ; a $end
$var wire 1 < b $end
$var wire 1 & cin $end
$var wire 1 % cout $end
$var wire 1 = stemp $end
$var wire 1 > s $end
$var wire 1 ? ctemp2 $end
$var wire 1 @ ctemp1 $end
$scope module ha1 $end
$var wire 1 ; a $end
$var wire 1 < b $end
$var wire 1 @ c $end
$var wire 1 = s $end
$upscope $end
$scope module ha2 $end
$var wire 1 = a $end
$var wire 1 & b $end
$var wire 1 ? c $end
$var wire 1 > s $end
$upscope $end
$upscope $end
$upscope $end
$upscope $end
$enddefinitions $end
$comment Show the parameter values. $end
$dumpall
$end
#0
$dumpvars
0@
0?
0>
0=
0<
0;
0:
09
08
07
06
05
04
03
02
01
00
0/
0.
0-
0,
0+
0*
0)
0(
0'
0&
0%
b0 $
0#
b0 "
b0 !
$end
#100000
b1 $
1,
1+
1*
b1 "
#200000
0,
b10 $
12
0+
11
0*
10
b10 "
#300000
b11 $
1,
1+
1*
b11 "
#400000
0,
02
b100 $
18
0+
01
17
0*
00
16
b100 "
#500000
b101 $
1,
1+
1*
b101 "
#600000
0,
b110 $
12
0+
11
0*
10
b110 "
#700000
b111 $
1,
1+
1*
b111 "
#800000
0,
02
08
b1000 $
1>
0+
01
07
1=
0*
00
06
1<
b1000 "
#900000
b1001 $
1,
1+
1*
b1001 "
#1000000
0,
b1010 $
12
0+
11
0*
10
b1010 "
#1100000
b1011 $
1,
1+
1*
b1011 "
#1200000
0,
02
b1100 $
18
0+
01
17
0*
00
16
b1100 "
#1300000
b1101 $
1,
1+
1*
b1101 "
#1400000
0,
b1110 $
12
0+
11
0*
10
b1110 "
#1500000
b1111 $
1,
1+
1*
b1111 "
#1600000
02
08
b1 $
0>
01
07
0=
0*
00
06
0<
1)
b0 "
b1 !
#1700000
12
b10 $
0,
1(
0+
1.
1*
b1 "
#1800000
08
0'
1,
0(
b11 $
12
03
1+
0.
11
0*
10
b10 "
#1900000
18
1'
02
13
b100 $
0,
1(
0+
1.
1*
b11 "
#2000000
0>
0'
0&
1,
0(
02
03
b101 $
18
09
1+
0.
01
17
0*
00
16
b100 "
#2100000
12
b110 $
0,
1(
0+
1.
1*
b101 "
#2200000
0>
0&
18
09
0'
1,
0(
b111 $
12
03
1+
0.
11
0*
10
b110 "
#2300000
1>
1&
08
19
1'
02
13
b1000 $
0,
1(
0+
1.
1*
b111 "
#2400000
0'
0&
0%
1,
0(
02
03
08
09
b1001 $
1>
0?
1+
0.
01
07
1=
0*
00
06
1<
b1000 "
#2500000
12
b1010 $
0,
1(
0+
1.
1*
b1001 "
#2600000
08
0'
1,
0(
b1011 $
12
03
1+
0.
11
0*
10
b1010 "
#2700000
18
1'
02
13
b1100 $
0,
1(
0+
1.
1*
b1011 "
#2800000
0%
1>
0?
0'
0&
1,
0(
02
03
b1101 $
18
09
1+
0.
01
17
0*
00
16
b1100 "
#2900000
12
b1110 $
0,
1(
0+
1.
1*
b1101 "
#3000000
0%
1>
0?
0&
18
09
0'
1,
0(
b1111 $
12
03
1+
0.
11
0*
10
b1110 "
#3100000
1%
0>
1?
1&
08
19
1'
02
13
b0 $
0,
1(
0+
1.
1*
b1111 "
#3200000
0'
0&
0%
12
03
08
09
b10 $
0>
0?
0(
07
0=
0.
0*
00
06
0<
0)
1/
b0 "
b10 !
#3300000
b11 $
1,
1+
1*
b1 "
#3400000
18
0,
b100 $
02
1'
0+
01
14
0*
10
b10 "
#3500000
b101 $
1,
1+
1*
b11 "
#3600000
0>
0&
0,
12
0'
b110 $
18
09
0+
11
04
17
0*
00
16
b100 "
#3700000
b111 $
1,
1+
1*
b101 "
#3800000
1>
1&
08
19
0,
b1000 $
02
1'
0+
01
14
0*
10
b110 "
#3900000
b1001 $
1,
1+
1*
b111 "
#4000000
0&
0%
0,
12
0'
08
09
b1010 $
1>
0?
0+
11
04
07
1=
0*
00
06
1<
b1000 "
#4100000
b1011 $
1,
1+
1*
b1001 "
#4200000
18
0,
b1100 $
02
1'
0+
01
14
0*
10
b1010 "
#4300000
b1101 $
1,
1+
1*
b1011 "
#4400000
0%
1>
0?
0&
0,
12
0'
b1110 $
18
09
0+
11
04
17
0*
00
16
b1100 "
#4500000
b1111 $
1,
1+
1*
b1101 "
#4600000
1%
0>
1?
1&
08
19
0,
b0 $
02
1'
0+
01
14
0*
10
b1110 "
#4700000
b1 $
1,
1+
1*
b1111 "
#4800000
0&
0%
12
0'
08
09
b11 $
0>
0?
11
04
07
0=
0*
00
06
0<
1)
b0 "
b11 !
#4900000
18
1'
02
13
b100 $
0,
1(
0+
1.
1*
b1 "
#5000000
1,
0(
b101 $
02
03
1+
0.
01
14
0*
10
b10 "
#5100000
12
b110 $
0,
1(
0+
1.
1*
b11 "
#5200000
0>
0&
1,
0(
12
03
0'
b111 $
18
09
1+
0.
11
04
17
0*
00
16
b100 "
#5300000
1>
1&
08
19
1'
02
13
b1000 $
0,
1(
0+
1.
1*
b101 "
#5400000
1,
0(
b1001 $
02
03
1+
0.
01
14
0*
10
b110 "
#5500000
12
b1010 $
0,
1(
0+
1.
1*
b111 "
#5600000
0&
0%
1,
0(
12
03
0'
08
09
b1011 $
1>
0?
1+
0.
11
04
07
1=
0*
00
06
1<
b1000 "
#5700000
18
1'
02
13
b1100 $
0,
1(
0+
1.
1*
b1001 "
#5800000
1,
0(
b1101 $
02
03
1+
0.
01
14
0*
10
b1010 "
#5900000
12
b1110 $
0,
1(
0+
1.
1*
b1011 "
#6000000
0%
1>
0?
0&
1,
0(
12
03
0'
b1111 $
18
09
1+
0.
11
04
17
0*
00
16
b1100 "
#6100000
1%
0>
1?
1&
08
19
1'
02
13
b0 $
0,
1(
0+
1.
1*
b1101 "
#6200000
1,
0(
b1 $
02
03
1+
0.
01
14
0*
10
b1110 "
#6300000
12
b10 $
0,
1(
0+
1.
1*
b1111 "
#6400000
0&
0%
02
18
09
b100 $
0>
0?
0(
0'
0=
0.
04
0*
00
06
0<
0)
0/
15
b0 "
b100 !
#6500000
b101 $
1,
1+
1*
b1 "
#6600000
0,
b110 $
12
0+
11
0*
10
b10 "
#6700000
b111 $
1,
1+
1*
b11 "
#6800000
1>
0,
02
b1000 $
08
1&
0+
01
07
1:
0*
00
16
b100 "
#6900000
b1001 $
1,
1+
1*
b101 "
#7000000
0,
b1010 $
12
0+
11
0*
10
b110 "
#7100000
b1011 $
1,
1+
1*
b111 "
#7200000
0%
0,
02
18
0&
b1100 $
1>
0?
0+
01
17
0:
1=
0*
00
06
1<
b1000 "
#7300000
b1101 $
1,
1+
1*
b1001 "
#7400000
0,
b1110 $
12
0+
11
0*
10
b1010 "
#7500000
b1111 $
1,
1+
1*
b1011 "
#7600000
1%
0>
1?
0,
02
b0 $
08
1&
0+
01
07
1:
0*
00
16
b1100 "
#7700000
b1 $
1,
1+
1*
b1101 "
#7800000
0,
b10 $
12
0+
11
0*
10
b1110 "
#7900000
b11 $
1,
1+
1*
b1111 "
#8000000
0%
02
18
0&
b101 $
0>
0?
01
17
0:
0=
0*
00
06
0<
1)
b0 "
b101 !
#8100000
12
b110 $
0,
1(
0+
1.
1*
b1 "
#8200000
0>
0&
18
09
0'
1,
0(
b111 $
12
03
1+
0.
11
0*
10
b10 "
#8300000
1>
1&
08
19
1'
02
13
b1000 $
0,
1(
0+
1.
1*
b11 "
#8400000
0'
1,
0(
02
03
b1001 $
08
09
1+
0.
01
07
1:
0*
00
16
b100 "
#8500000
12
b1010 $
0,
1(
0+
1.
1*
b101 "
#8600000
08
0'
1,
0(
b1011 $
12
03
1+
0.
11
0*
10
b110 "
#8700000
18
1'
02
13
b1100 $
0,
1(
0+
1.
1*
b111 "
#8800000
0'
0%
1,
0(
02
03
18
09
0&
b1101 $
1>
0?
1+
0.
01
17
0:
1=
0*
00
06
1<
b1000 "
#8900000
12
b1110 $
0,
1(
0+
1.
1*
b1001 "
#9000000
0%
1>
0?
0&
18
09
0'
1,
0(
b1111 $
12
03
1+
0.
11
0*
10
b1010 "
#9100000
1%
0>
1?
1&
08
19
1'
02
13
b0 $
0,
1(
0+
1.
1*
b1011 "
#9200000
0'
1,
0(
02
03
b1 $
08
09
1+
0.
01
07
1:
0*
00
16
b1100 "
#9300000
12
b10 $
0,
1(
0+
1.
1*
b1101 "
#9400000
08
0'
1,
0(
b11 $
12
03
1+
0.
11
0*
10
b1110 "
#9500000
18
1'
02
13
b100 $
0,
1(
0+
1.
1*
b1111 "
#9600000
0'
0%
12
03
18
09
0&
b110 $
0>
0?
0(
17
0:
0=
0.
0*
00
06
0<
0)
1/
b0 "
b110 !
#9700000
b111 $
1,
1+
1*
b1 "
#9800000
1>
1&
08
19
0,
b1000 $
02
1'
0+
01
14
0*
10
b10 "
#9900000
b1001 $
1,
1+
1*
b11 "
#10000000
0,
12
0'
b1010 $
08
09
0+
11
04
07
1:
0*
00
16
b100 "
#10100000
b1011 $
1,
1+
1*
b101 "
#10200000
18
0,
b1100 $
02
1'
0+
01
14
0*
10
b110 "
#10300000
b1101 $
1,
1+
1*
b111 "
#10400000
0%
0,
12
0'
18
09
0&
b1110 $
1>
0?
0+
11
04
17
0:
1=
0*
00
06
1<
b1000 "
#10500000
b1111 $
1,
1+
1*
b1001 "
#10600000
1%
0>
1?
1&
08
19
0,
b0 $
02
1'
0+
01
14
0*
10
b1010 "
#10700000
b1 $
1,
1+
1*
b1011 "
#10800000
0,
12
0'
b10 $
08
09
0+
11
04
07
1:
0*
00
16
b1100 "
#10900000
b11 $
1,
1+
1*
b1101 "
#11000000
18
0,
b100 $
02
1'
0+
01
14
0*
10
b1110 "
#11100000
b101 $
1,
1+
1*
b1111 "
#11200000
0%
12
0'
18
09
0&
b111 $
0>
0?
11
04
17
0:
0=
0*
00
06
0<
1)
b0 "
b111 !
#11300000
1>
1&
08
19
1'
02
13
b1000 $
0,
1(
0+
1.
1*
b1 "
#11400000
1,
0(
b1001 $
02
03
1+
0.
01
14
0*
10
b10 "
#11500000
12
b1010 $
0,
1(
0+
1.
1*
b11 "
#11600000
1,
0(
12
03
0'
b1011 $
08
09
1+
0.
11
04
07
1:
0*
00
16
b100 "
#11700000
18
1'
02
13
b1100 $
0,
1(
0+
1.
1*
b101 "
#11800000
1,
0(
b1101 $
02
03
1+
0.
01
14
0*
10
b110 "
#11900000
12
b1110 $
0,
1(
0+
1.
1*
b111 "
#12000000
0%
1,
0(
12
03
0'
18
09
0&
b1111 $
1>
0?
1+
0.
11
04
17
0:
1=
0*
00
06
1<
b1000 "
#12100000
1%
0>
1?
1&
08
19
1'
02
13
b0 $
0,
1(
0+
1.
1*
b1001 "
#12200000
1,
0(
b1 $
02
03
1+
0.
01
14
0*
10
b1010 "
#12300000
12
b10 $
0,
1(
0+
1.
1*
b1011 "
#12400000
1,
0(
12
03
0'
b11 $
08
09
1+
0.
11
04
07
1:
0*
00
16
b1100 "
#12500000
18
1'
02
13
b100 $
0,
1(
0+
1.
1*
b1101 "
#12600000
1,
0(
b101 $
02
03
1+
0.
01
14
0*
10
b1110 "
#12700000
12
b110 $
0,
1(
0+
1.
1*
b1111 "
#12800000
0%
02
08
b1000 $
1>
0?
0(
0'
0&
0.
04
0:
0*
00
06
0<
0)
0/
05
1;
b0 "
b1000 !
#12900000
b1001 $
1,
1+
1*
b1 "
#13000000
0,
b1010 $
12
0+
11
0*
10
b10 "
#13100000
b1011 $
1,
1+
1*
b11 "
#13200000
0,
02
b1100 $
18
0+
01
17
0*
00
16
b100 "
#13300000
b1101 $
1,
1+
1*
b101 "
#13400000
0,
b1110 $
12
0+
11
0*
10
b110 "
#13500000
b1111 $
1,
1+
1*
b111 "
#13600000
0,
02
08
b0 $
0>
1%
0+
01
07
0=
1@
0*
00
06
1<
b1000 "
#13700000
b1 $
1,
1+
1*
b1001 "
#13800000
0,
b10 $
12
0+
11
0*
10
b1010 "
#13900000
b11 $
1,
1+
1*
b1011 "
#14000000
0,
02
b100 $
18
0+
01
17
0*
00
16
b1100 "
#14100000
b101 $
1,
1+
1*
b1101 "
#14200000
0,
b110 $
12
0+
11
0*
10
b1110 "
#14300000
b111 $
1,
1+
1*
b1111 "
#14400000
02
08
b1001 $
1>
0%
01
07
1=
0@
0*
00
06
0<
1)
b0 "
b1001 !
#14500000
12
b1010 $
0,
1(
0+
1.
1*
b1 "
#14600000
08
0'
1,
0(
b1011 $
12
03
1+
0.
11
0*
10
b10 "
#14700000
18
1'
02
13
b1100 $
0,
1(
0+
1.
1*
b11 "
#14800000
0%
1>
0?
0'
0&
1,
0(
02
03
b1101 $
18
09
1+
0.
01
17
0*
00
16
b100 "
#14900000
12
b1110 $
0,
1(
0+
1.
1*
b101 "
#15000000
0%
1>
0?
0&
18
09
0'
1,
0(
b1111 $
12
03
1+
0.
11
0*
10
b110 "
#15100000
1%
0>
1?
1&
08
19
1'
02
13
b0 $
0,
1(
0+
1.
1*
b111 "
#15200000
0'
0&
1,
0(
02
03
08
09
b1 $
0>
0?
1+
0.
01
07
0=
1@
0*
00
06
1<
b1000 "
#15300000
12
b10 $
0,
1(
0+
1.
1*
b1001 "
#15400000
08
0'
1,
0(
b11 $
12
03
1+
0.
11
0*
10
b1010 "
#15500000
18
1'
02
13
b100 $
0,
1(
0+
1.
1*
b1011 "
#15600000
0>
0'
0&
1,
0(
02
03
b101 $
18
09
1+
0.
01
17
0*
00
16
b1100 "
#15700000
12
b110 $
0,
1(
0+
1.
1*
b1101 "
#15800000
0>
0&
18
09
0'
1,
0(
b111 $
12
03
1+
0.
11
0*
10
b1110 "
#15900000
1>
1&
08
19
1'
02
13
b1000 $
0,
1(
0+
1.
1*
b1111 "
#16000000
0'
0&
12
03
08
09
b1010 $
1>
0?
0%
0(
07
1=
0@
0.
0*
00
06
0<
0)
1/
b0 "
b1010 !
#16100000
b1011 $
1,
1+
1*
b1 "
#16200000
18
0,
b1100 $
02
1'
0+
01
14
0*
10
b10 "
#16300000
b1101 $
1,
1+
1*
b11 "
#16400000
0%
1>
0?
0&
0,
12
0'
b1110 $
18
09
0+
11
04
17
0*
00
16
b100 "
#16500000
b1111 $
1,
1+
1*
b101 "
#16600000
1%
0>
1?
1&
08
19
0,
b0 $
02
1'
0+
01
14
0*
10
b110 "
#16700000
b1 $
1,
1+
1*
b111 "
#16800000
0&
0,
12
0'
08
09
b10 $
0>
0?
0+
11
04
07
0=
1@
0*
00
06
1<
b1000 "
#16900000
b11 $
1,
1+
1*
b1001 "
#17000000
18
0,
b100 $
02
1'
0+
01
14
0*
10
b1010 "
#17100000
b101 $
1,
1+
1*
b1011 "
#17200000
0>
0&
0,
12
0'
b110 $
18
09
0+
11
04
17
0*
00
16
b1100 "
#17300000
b111 $
1,
1+
1*
b1101 "
#17400000
1>
1&
08
19
0,
b1000 $
02
1'
0+
01
14
0*
10
b1110 "
#17500000
b1001 $
1,
1+
1*
b1111 "
#17600000
0&
12
0'
08
09
b1011 $
1>
0?
0%
11
04
07
1=
0@
0*
00
06
0<
1)
b0 "
b1011 !
#17700000
18
1'
02
13
b1100 $
0,
1(
0+
1.
1*
b1 "
#17800000
1,
0(
b1101 $
02
03
1+
0.
01
14
0*
10
b10 "
#17900000
12
b1110 $
0,
1(
0+
1.
1*
b11 "
#18000000
0%
1>
0?
0&
1,
0(
12
03
0'
b1111 $
18
09
1+
0.
11
04
17
0*
00
16
b100 "
#18100000
1%
0>
1?
1&
08
19
1'
02
13
b0 $
0,
1(
0+
1.
1*
b101 "
#18200000
1,
0(
b1 $
02
03
1+
0.
01
14
0*
10
b110 "
#18300000
12
b10 $
0,
1(
0+
1.
1*
b111 "
#18400000
0&
1,
0(
12
03
0'
08
09
b11 $
0>
0?
1+
0.
11
04
07
0=
1@
0*
00
06
1<
b1000 "
#18500000
18
1'
02
13
b100 $
0,
1(
0+
1.
1*
b1001 "
#18600000
1,
0(
b101 $
02
03
1+
0.
01
14
0*
10
b1010 "
#18700000
12
b110 $
0,
1(
0+
1.
1*
b1011 "
#18800000
0>
0&
1,
0(
12
03
0'
b111 $
18
09
1+
0.
11
04
17
0*
00
16
b1100 "
#18900000
1>
1&
08
19
1'
02
13
b1000 $
0,
1(
0+
1.
1*
b1101 "
#19000000
1,
0(
b1001 $
02
03
1+
0.
01
14
0*
10
b1110 "
#19100000
12
b1010 $
0,
1(
0+
1.
1*
b1111 "
#19200000
0&
02
18
09
b1100 $
1>
0?
0%
0(
0'
1=
0@
0.
04
0*
00
06
0<
0)
0/
15
b0 "
b1100 !
#19300000
b1101 $
1,
1+
1*
b1 "
#19400000
0,
b1110 $
12
0+
11
0*
10
b10 "
#19500000
b1111 $
1,
1+
1*
b11 "
#19600000
1%
0>
1?
0,
02
b0 $
08
1&
0+
01
07
1:
0*
00
16
b100 "
#19700000
b1 $
1,
1+
1*
b101 "
#19800000
0,
b10 $
12
0+
11
0*
10
b110 "
#19900000
b11 $
1,
1+
1*
b111 "
#20000000
0,
02
18
0&
b100 $
0>
0?
0+
01
17
0:
0=
1@
0*
00
06
1<
b1000 "
#20100000
b101 $
1,
1+
1*
b1001 "
#20200000
0,
b110 $
12
0+
11
0*
10
b1010 "
#20300000
b111 $
1,
1+
1*
b1011 "
#20400000
1>
0,
02
b1000 $
08
1&
0+
01
07
1:
0*
00
16
b1100 "
#20500000
b1001 $
1,
1+
1*
b1101 "
#20600000
0,
b1010 $
12
0+
11
0*
10
b1110 "
#20700000
b1011 $
1,
1+
1*
b1111 "
#20800000
02
18
0&
b1101 $
1>
0?
0%
01
17
0:
1=
0@
0*
00
06
0<
1)
b0 "
b1101 !
#20900000
12
b1110 $
0,
1(
0+
1.
1*
b1 "
#21000000
0%
1>
0?
0&
18
09
0'
1,
0(
b1111 $
12
03
1+
0.
11
0*
10
b10 "
#21100000
1%
0>
1?
1&
08
19
1'
02
13
b0 $
0,
1(
0+
1.
1*
b11 "
#21200000
0'
1,
0(
02
03
b1 $
08
09
1+
0.
01
07
1:
0*
00
16
b100 "
#21300000
12
b10 $
0,
1(
0+
1.
1*
b101 "
#21400000
08
0'
1,
0(
b11 $
12
03
1+
0.
11
0*
10
b110 "
#21500000
18
1'
02
13
b100 $
0,
1(
0+
1.
1*
b111 "
#21600000
0'
1,
0(
02
03
18
09
0&
b101 $
0>
0?
1+
0.
01
17
0:
0=
1@
0*
00
06
1<
b1000 "
#21700000
12
b110 $
0,
1(
0+
1.
1*
b1001 "
#21800000
0>
0&
18
09
0'
1,
0(
b111 $
12
03
1+
0.
11
0*
10
b1010 "
#21900000
1>
1&
08
19
1'
02
13
b1000 $
0,
1(
0+
1.
1*
b1011 "
#22000000
0'
1,
0(
02
03
b1001 $
08
09
1+
0.
01
07
1:
0*
00
16
b1100 "
#22100000
12
b1010 $
0,
1(
0+
1.
1*
b1101 "
#22200000
08
0'
1,
0(
b1011 $
12
03
1+
0.
11
0*
10
b1110 "
#22300000
18
1'
02
13
b1100 $
0,
1(
0+
1.
1*
b1111 "
#22400000
0'
12
03
18
09
0&
b1110 $
1>
0?
0%
0(
17
0:
1=
0@
0.
0*
00
06
0<
0)
1/
b0 "
b1110 !
#22500000
b1111 $
1,
1+
1*
b1 "
#22600000
1%
0>
1?
1&
08
19
0,
b0 $
02
1'
0+
01
14
0*
10
b10 "
#22700000
b1 $
1,
1+
1*
b11 "
#22800000
0,
12
0'
b10 $
08
09
0+
11
04
07
1:
0*
00
16
b100 "
#22900000
b11 $
1,
1+
1*
b101 "
#23000000
18
0,
b100 $
02
1'
0+
01
14
0*
10
b110 "
#23100000
b101 $
1,
1+
1*
b111 "
#23200000
0,
12
0'
18
09
0&
b110 $
0>
0?
0+
11
04
17
0:
0=
1@
0*
00
06
1<
b1000 "
#23300000
b111 $
1,
1+
1*
b1001 "
#23400000
1>
1&
08
19
0,
b1000 $
02
1'
0+
01
14
0*
10
b1010 "
#23500000
b1001 $
1,
1+
1*
b1011 "
#23600000
0,
12
0'
b1010 $
08
09
0+
11
04
07
1:
0*
00
16
b1100 "
#23700000
b1011 $
1,
1+
1*
b1101 "
#23800000
18
0,
b1100 $
02
1'
0+
01
14
0*
10
b1110 "
#23900000
b1101 $
1,
1+
1*
b1111 "
#24000000
12
0'
18
09
0&
b1111 $
1>
0?
0%
11
04
17
0:
1=
0@
0*
00
06
0<
1)
b0 "
b1111 !
#24100000
1%
0>
1?
1&
08
19
1'
02
13
b0 $
0,
1(
0+
1.
1*
b1 "
#24200000
1,
0(
b1 $
02
03
1+
0.
01
14
0*
10
b10 "
#24300000
12
b10 $
0,
1(
0+
1.
1*
b11 "
#24400000
1,
0(
12
03
0'
b11 $
08
09
1+
0.
11
04
07
1:
0*
00
16
b100 "
#24500000
18
1'
02
13
b100 $
0,
1(
0+
1.
1*
b101 "
#24600000
1,
0(
b101 $
02
03
1+
0.
01
14
0*
10
b110 "
#24700000
12
b110 $
0,
1(
0+
1.
1*
b111 "
#24800000
1,
0(
12
03
0'
18
09
0&
b111 $
0>
0?
1+
0.
11
04
17
0:
0=
1@
0*
00
06
1<
b1000 "
#24900000
1>
1&
08
19
1'
02
13
b1000 $
0,
1(
0+
1.
1*
b1001 "
#25000000
1,
0(
b1001 $
02
03
1+
0.
01
14
0*
10
b1010 "
#25100000
12
b1010 $
0,
1(
0+
1.
1*
b1011 "
#25200000
1,
0(
12
03
0'
b1011 $
08
09
1+
0.
11
04
07
1:
0*
00
16
b1100 "
#25300000
18
1'
02
13
b1100 $
0,
1(
0+
1.
1*
b1101 "
#25400000
1,
0(
b1101 $
02
03
1+
0.
01
14
0*
10
b1110 "
#25500000
12
b1110 $
0,
1(
0+
1.
1*
b1111 "
#25600000
02
08
0>
0(
0'
0&
0%
0.
04
0:
0@
b1 $
1,
0*
00
06
0<
0)
0/
05
0;
1#
b0 "
b0 !
#25700000
12
1(
b10 $
0,
1-
1+
1*
b1 "
#25800000
08
0(
0'
1,
0-
b11 $
12
03
0+
11
0*
10
b10 "
#25900000
18
1'
02
13
1(
b100 $
0,
1-
1+
1*
b11 "
#26000000
0>
0(
0'
0&
1,
0-
02
03
b101 $
18
09
0+
01
17
0*
00
16
b100 "
#26100000
12
1(
b110 $
0,
1-
1+
1*
b101 "
#26200000
0>
0&
18
09
0(
0'
1,
0-
b111 $
12
03
0+
11
0*
10
b110 "
#26300000
1>
1&
08
19
1'
02
13
1(
b1000 $
0,
1-
1+
1*
b111 "
#26400000
0(
0'
0&
0%
1,
0-
02
03
08
09
b1001 $
1>
0?
0+
01
07
1=
0*
00
06
1<
b1000 "
#26500000
12
1(
b1010 $
0,
1-
1+
1*
b1001 "
#26600000
08
0(
0'
1,
0-
b1011 $
12
03
0+
11
0*
10
b1010 "
#26700000
18
1'
02
13
1(
b1100 $
0,
1-
1+
1*
b1011 "
#26800000
0%
1>
0?
0(
0'
0&
1,
0-
02
03
b1101 $
18
09
0+
01
17
0*
00
16
b1100 "
#26900000
12
1(
b1110 $
0,
1-
1+
1*
b1101 "
#27000000
0%
1>
0?
0&
18
09
0(
0'
1,
0-
b1111 $
12
03
0+
11
0*
10
b1110 "
#27100000
1%
0>
1?
1&
08
19
1'
02
13
1(
b0 $
0,
1-
1+
1*
b1111 "
#27200000
0'
0&
0%
12
03
08
09
b10 $
0>
0?
01
07
0=
0*
00
06
0<
1)
b0 "
b1 !
#27300000
b11 $
1,
0-
0+
1.
1*
b1 "
#27400000
18
1'
0,
1-
1(
b100 $
02
13
1+
0.
11
0*
10
b10 "
#27500000
b101 $
1,
0-
0+
1.
1*
b11 "
#27600000
0>
0'
0&
0,
1-
1(
12
03
b110 $
18
09
1+
0.
01
17
0*
00
16
b100 "
#27700000
b111 $
1,
0-
0+
1.
1*
b101 "
#27800000
1>
1&
08
19
1'
0,
1-
1(
b1000 $
02
13
1+
0.
11
0*
10
b110 "
#27900000
b1001 $
1,
0-
0+
1.
1*
b111 "
#28000000
0'
0&
0%
0,
1-
1(
12
03
08
09
b1010 $
1>
0?
1+
0.
01
07
1=
0*
00
06
1<
b1000 "
#28100000
b1011 $
1,
0-
0+
1.
1*
b1001 "
#28200000
18
1'
0,
1-
1(
b1100 $
02
13
1+
0.
11
0*
10
b1010 "
#28300000
b1101 $
1,
0-
0+
1.
1*
b1011 "
#28400000
0%
1>
0?
0'
0&
0,
1-
1(
12
03
b1110 $
18
09
1+
0.
01
17
0*
00
16
b1100 "
#28500000
b1111 $
1,
0-
0+
1.
1*
b1101 "
#28600000
1%
0>
1?
1&
08
19
1'
0,
1-
1(
b0 $
02
13
1+
0.
11
0*
10
b1110 "
#28700000
b1 $
1,
0-
0+
1.
1*
b1111 "
#28800000
0'
0&
0%
12
03
08
09
b11 $
0>
0?
0(
07
0=
0.
0*
00
06
0<
0)
1/
b0 "
b10 !
#28900000
18
1'
02
13
1(
b100 $
0,
1-
1+
1*
b1 "
#29000000
0(
1,
0-
b101 $
02
03
0+
01
14
0*
10
b10 "
#29100000
12
1(
b110 $
0,
1-
1+
1*
b11 "
#29200000
0>
0(
0&
1,
0-
12
03
0'
b111 $
18
09
0+
11
04
17
0*
00
16
b100 "
#29300000
1>
1&
08
19
1'
02
13
1(
b1000 $
0,
1-
1+
1*
b101 "
#29400000
0(
1,
0-
b1001 $
02
03
0+
01
14
0*
10
b110 "
#29500000
12
1(
b1010 $
0,
1-
1+
1*
b111 "
#29600000
0(
0&
0%
1,
0-
12
03
0'
08
09
b1011 $
1>
0?
0+
11
04
07
1=
0*
00
06
1<
b1000 "
#29700000
18
1'
02
13
1(
b1100 $
0,
1-
1+
1*
b1001 "
#29800000
0(
1,
0-
b1101 $
02
03
0+
01
14
0*
10
b1010 "
#29900000
12
1(
b1110 $
0,
1-
1+
1*
b1011 "
#30000000
0%
1>
0?
0(
0&
1,
0-
12
03
0'
b1111 $
18
09
0+
11
04
17
0*
00
16
b1100 "
#30100000
1%
0>
1?
1&
08
19
1'
02
13
1(
b0 $
0,
1-
1+
1*
b1101 "
#30200000
0(
1,
0-
b1 $
02
03
0+
01
14
0*
10
b1110 "
#30300000
12
1(
b10 $
0,
1-
1+
1*
b1111 "
#30400000
0&
0%
02
13
1'
18
09
b100 $
0>
0?
11
04
07
0=
0*
00
06
0<
1)
b0 "
b11 !
#30500000
b101 $
1,
0-
0+
1.
1*
b1 "
