lab1/half_adder.v
module half_adder(input a, b, output s,c);
 xor(s,a,b);
 and(c,a,b);
endmodule;

lab1/full_adder.v
module full_adder(input a, b, cin, output s, cout);
 wire stemp, ctemp1, ctemp2;

 half_adder ha1(.a(a), .b(b), .s(stemp), .c(ctemp1));
 half_adder ha2(.a(stemp), .b(cin), .s(s), .c(ctemp2));
 or(cout, ctemp1, ctemp2);

endmodule

lab1/testbench/full_adder_tb.sv
`timescale 1ns/1ps

module full_adder_tb();
 reg a, b, cin;
 wire cout, s;
 full_adder fa(.a(a), .b(b), .cin(cin), .s(s), .cout(cout));
 initial begin
  $dumpfile("full_adder.vcd");
  $dumpvars(0,fa);

  a=0;b=0;cin=0; #100;
  a=0;b=1;cin=0; #100;
  a=1;b=0;cin=0; #100;
  a=1;b=1;cin=0; #100;

  a=0;b=0;cin=1; #100;
  a=0;b=1;cin=1; #100;
  a=1;b=0;cin=1; #100;
  a=1;b=1;cin=1; #100;

  $finish;
 end 
endmodule

lab1/full_adder.vcd
$date
	Thu Jun 18 23:04:47 2026
$end
$version
	Icarus Verilog
$end
$timescale
	1ps
$end
$scope module full_adder_tb $end
$scope module fa $end
$var wire 1 ! a $end
$var wire 1 " b $end
$var wire 1 # cin $end
$var wire 1 $ cout $end
$var wire 1 % stemp $end
$var wire 1 & s $end
$var wire 1 ' ctemp2 $end
$var wire 1 ( ctemp1 $end
$scope module ha1 $end
$var wire 1 ! a $end
$var wire 1 " b $end
$var wire 1 ( c $end
$var wire 1 % s $end
$upscope $end
$scope module ha2 $end
$var wire 1 % a $end
$var wire 1 # b $end
$var wire 1 ' c $end
$var wire 1 & s $end
$upscope $end
$upscope $end
$upscope $end
$enddefinitions $end
$comment Show the parameter values. $end
$dumpall
$end
#0
$dumpvars
0(
0'
0&
0%
0$
0#
0"
0!
$end
#100000
1&
1%
1"
#200000
0"
1!
#300000
0&
1$
0%
1(
1"
#400000
0$
1&
0(
1#
0"
0!
#500000
1$
0&
1'
1%
1"
#600000
0"
1!
#700000
1&
0'
0%
1(
1"
